[
    {
        "location": "Leer (Ostfriesland), Niedersachen",
        "timespan": "04.2026 - XXXX",
        "company": "Bfw-Unternehmen für Bildung",
        "logo": "https://media.licdn.com/dms/image/v2/D4E0BAQGvoUu6PGVt2Q/company-logo_100_100/B4EZzikRhlIUAQ-/0/1773327686410/bfw_unternehmen_fuer_bildung_logo?e=1775692800&v=beta&t=QuGfR50-sDV52_PU23llIIQaC3Kh9i3B3Et9IHWUOKE",
        "profession": "Umschulung zum Elektroniker für Betriebstechnik",
        "description": "Beschreibung kommt bald...",
        "tasks": [
            "Projektierung und Installation elektrischer Anlagen: Planung und Realisierung komplexer Systeme der Energieversorgung sowie Beleuchtungs- und Antriebstechnik unter strikter Einhaltung der geltenden VDE-Normen.",
            "Automatisierung und SPS-Programmierung: Konfigurierung und Programmierung speicherprogrammierbarer Steuerungen, binde Sensorik sowie Aktorik an und optimiere so industrielle Prozessabläufe.",
            "Systematische Instandhaltung und Fehlersuche: Analyse elektrischer Schutzmaßnahmen, regelmäßige Prüfungen und Behebung von Störungen in vernetzten Produktionsanlagen zur Sicherstellung der Betriebsbereitschaft."
        ],
        "tags": [
            "umschulung",
            "weiterbildung",
            "ausbildung"
        ]
    },
    {
        "location": "Berlin (Remote)",
        "timespan": "02.2026 - 04.2026",
        "company": "Webeet.io",
        "logo": "https://media.licdn.com/dms/image/v2/D4E0BAQFCEsNI76yZAg/company-logo_100_100/B4EZyT8uxXIEAQ-/0/1772008697279/webeet_logo?e=1775692800&v=beta&t=XnY7z5jzo_2oZLhzx717ErBFPPLRTcrgeikAw5WK1Uw",
        "profession": "Praktikum als Backend-Entwickler",
        "description": "Pflichtpraktikum im Rahmen der Weiterbildung bei der Masterschool",
        "tasks": [
            "Entwickeln von effizienten APIs: Modularität mit Fastify und FastAPI - NextJS.",
            "Implementierung serverseitiger Logik mit TypeScript - Striktes ZOD Schema und SQL Lite",
            "Sicherstellung der Codequalität & Zuverlässigkeit...: Aufrechterhaltung hoher standards durch TDD mit Jest."
        ],
        "tags": [
            "weiterbildung",
            "praktikum"
        ]
    }
    ,
    {
        "location": "Berlin (Remote)",
        "timespan": "02.2025 - 04.2026",
        "company": "Masterschool",
        "logo": "https://media.licdn.com/dms/image/v2/D4D0BAQGWJWf8c0q3SQ/company-logo_100_100/B4DZZXd_VpHwAQ-/0/1745224202049/joinmasterschool_logo?e=1775692800&v=beta&t=0lIOU6f5AVOhqG7bNEFPaqGt8w2HRBqzBsDeaM3swdI",
        "profession": "Weiterbildung zum Backend-Entwickler",
        "description": "Erweiterung und Festigung meiner Fähigkeiten im Programmieren.",
        "tasks": [
            "Entwicklung von Backend-Applikationen mit Python, TypeScript, JavaScript & SQL - Überwiegend mit Flask",
            "Anwendung von Objekt-Orientierter Programmierung und Test-driven Development",
            "Einsetzen von Git, GitHub & GitLab für Versionskontrolle",
            "Erweiterung meiner autodidaktischen Kenntnisse in Python, HTML, CSS, Batch(CMD) & JavaScript"
        ],
        "tags": [
            "weiterbildung"
        ]
    }
    ,
    {
        "location": "Emden, Niedersachsen",
        "timespan": "03.2024 - 06.2024",
        "company": "Akademie Überlingen",
        "logo": "https://media.licdn.com/dms/image/v2/C4D0BAQFCXCz69fjU1A/company-logo_100_100/company-logo_100_100/0/1630527626225/akademie_berlingen_verwaltungs_logo?e=1775692800&v=beta&t=uyrQ1jiCw_qn2_pI-wvtDpRfEiWHluh0ytw2l-bUKjc",
        "profession": "Weiterbildung zum Auslieferungsfahrer",
        "description": "...",
        "tasks": [
            "Erhalt des Führerscheines der Klasse B"
        ],
        "tags": [
            "weiterbildung"
        ]
    }
    ,
    {
        "location": "Emden, Niedersachsen",
        "timespan": "05.2023 - 11.2023",
        "company": "<Auf Anfrage>",
        "logo": "",
        "profession": "Verkäufer",
        "description": "...",
        "tasks": [
            "Kundenbedienung",
            "Kassieren",
            "Warenverräumung",
            "Inventur"
        ],
        "tags": [
            "arbeit"
        ]
    }
    ,
    {
        "location": "Emden, Niedersachsen",
        "timespan": "11.2021 - 05.2023",
        "company": "<Auf Anfrage>",
        "logo": "",
        "profession": "Staplerfahrer",
        "description": "...",
        "tasks": [
            "Verladen: Vollgut & Leergut",
            "Einlagern & Auslagern",
            "Umfuhr, Zählung / Inventur & Bereitstellung"
        ],
        "tags": [
            "arbeit"
        ]
    }
    ,
    {
        "location": "Emden, Niedersachsen",
        "timespan": "08.2020 - 01.2021",
        "company": "BBS II Emden",
        "logo": "",
        "profession": "Berufsfachschule - Metalltechnik (Anlagenmechaniker)",
        "description": "",
        "tasks": [
            
        ],
        "tags": [
            "bfs",
            "berufsfachschule",
            "ausbildung"
        ]
    }
    ,
    {
        "location": "Emden, Niedersachsen",
        "timespan": "08.2019 - 06.2020",
        "company": "BBS II Emden",
        "logo": "",
        "profession": "Berufsfachschule - KFZ Mechatroniker",
        "description": "",
        "tasks": [
            
        ],
        "tags": [
            "bfs",
            "berufsfachschule",
            "ausbildung"
        ]
    }
    ,
    {
        "location": "Surwold, Niedersachsen",
        "timespan": "09.2017 - 12.2017",
        "company": "Baustoffe Gerdes",
        "logo": "",
        "profession": "Praktikum als Lagermitarbeiter",
        "description": "",
        "tasks": [
            
        ],
        "tags": [
            "praktikum"
        ]
    }
    ,
    {
        "location": "Surwold, Niedersachsen",
        "timespan": "10.2016 - 02.2017",
        "company": "Baustoffe Gerdes",
        "logo": "",
        "profession": "Praktikum als Lagermitarbeiter",
        "description": "",
        "tasks": [
            
        ],
        "tags": [
            "praktikum"
        ]
    }
]